uservice_logging/__init__.py
uservice_logging/logging.py
uservice_logging/tests/__init__.py
uservice_logging/tests/test_logging.py
uservice_logging-0.10.2.dist-info/DESCRIPTION.rst
uservice_logging-0.10.2.dist-info/METADATA
uservice_logging-0.10.2.dist-info/RECORD
uservice_logging-0.10.2.dist-info/WHEEL
uservice_logging-0.10.2.dist-info/metadata.json
uservice_logging-0.10.2.dist-info/top_level.txt
